paginator.py
setup.py
Paginator.egg-info/PKG-INFO
Paginator.egg-info/SOURCES.txt
Paginator.egg-info/dependency_links.txt
Paginator.egg-info/not-zip-safe
Paginator.egg-info/pbr.json
Paginator.egg-info/requires.txt
Paginator.egg-info/top_level.txt