Metadata-Version: 1.1
Name: Paginator
Version: 0.3.1
Summary: Paginator for SQLAlchemy query object, list or iterable 
Home-page: http://github.com/mardix/paginator.py/
Author: Mardix
Author-email: mardix@pylot.io
License: MIT
Download-URL: http://github.com/mardix/paginator.py/tarball/master
Keywords: pagination,paginate,page,flask,jinja2,sqlalchemy
Platform: any
Classifier: Environment :: Web Environment
Classifier: Intended Audience :: Developers
Classifier: License :: OSI Approved :: BSD License
Classifier: Operating System :: OS Independent
Classifier: Programming Language :: Python
Classifier: Programming Language :: Python :: 2
Classifier: Programming Language :: Python :: 2.6
Classifier: Programming Language :: Python :: 2.7
Classifier: Programming Language :: Python :: 3
Classifier: Programming Language :: Python :: 3.3
Classifier: Topic :: Internet :: WWW/HTTP :: Dynamic Content
Classifier: Topic :: Software Development :: Libraries :: Python Modules
